[
		{
			"data": {
				"id": "CSK",
				"name": "CSK",
				"weight": 0.19476744186046513
			},
			"classes": "intrinsic"
		},
		{
			"data": {
				"id": "FABP3",
				"name": "FABP3",
				"weight": 0.020348837209302327
			},
			"classes": "associated"
		},
		{
			"data": {
				"id": "ITGA1",
				"name": "ITGA1",
				"weight": 0.023255813953488372
			},
			"classes": "intrinsic central"
		},
		{
			"data": {
				"id": "ITGB1",
				"name": "ITGB1",
				"weight": 0.37209302325581395
			},
			"classes": "intrinsic"
		},
		{
			"data": {
				"id": "PTPN2",
				"name": "PTPN2",
				"weight": 0.023255813953488372
			},
			"classes": "associated"
		},
		{
			"data": {
				"id": "SHARPIN",
				"name": "SHARPIN",
				"weight": 0.01744186046511628
			},
			"classes": "associated"
		},
		{
			"data": {
				"id": "TLN1",
				"name": "TLN1",
				"weight": 0.125
			},
			"classes": "intrinsic"
		},
		{
			"data": {
				"id": 0,
				"source": "ITGB1",
				"target": "TLN1",
				"pmid": "10497223"
			}
		},		{
			"data": {
				"id": 1,
				"source": "ITGA1",
				"target": "TLN1",
				"pmid": "11336656"
			}
		},		{
			"data": {
				"id": 2,
				"source": "ITGA1",
				"target": "PTPN2",
				"pmid": "15592458"
			}
		},		{
			"data": {
				"id": 3,
				"source": "ITGA1",
				"target": "ITGB1",
				"pmid": "8846021"
			}
		},		{
			"data": {
				"id": 4,
				"source": "ITGA1",
				"target": "SHARPIN",
				"pmid": "21947080"
			}
		},		{
			"data": {
				"id": 5,
				"source": "CSK",
				"target": "ITGB1",
				"pmid": "10592173"
			}
		},		{
			"data": {
				"id": 6,
				"source": "CSK",
				"target": "ITGA1",
				"pmid": "10592173"
			}
		},		{
			"data": {
				"id": 7,
				"source": "ITGB1",
				"target": "SHARPIN",
				"pmid": "21947080"
			}
		},		{
			"data": {
				"id": 8,
				"source": "FABP3",
				"target": "ITGB1",
				"pmid": "20802519"
			}
		},		{
			"data": {
				"id": 9,
				"source": "FABP3",
				"target": "ITGA1",
				"pmid": "20802519"
			}
		}]